uupt_mcp_server/__init__.py
uupt_mcp_server/__main__.py
uupt_mcp_server/order.py
uupt_mcp_server_aaron-0.2.4.dist-info/licenses/LICENSE
uupt_mcp_server_aaron-0.2.4.dist-info/METADATA
uupt_mcp_server_aaron-0.2.4.dist-info/WHEEL
uupt_mcp_server_aaron-0.2.4.dist-info/entry_points.txt
uupt_mcp_server_aaron-0.2.4.dist-info/top_level.txt
uupt_mcp_server_aaron-0.2.4.dist-info/RECORD
