Metadata-Version: 2.4
Name: uupt-mcp-server-aaron
Version: 0.2.4
Summary: uupt.com openapi mcp server
Requires-Python: >=3.11.0
License-File: LICENSE
Requires-Dist: httpx>=0.28.1
Requires-Dist: mcp[cli]>=1.6.0
Requires-Dist: requests>=2.32.3
Dynamic: license-file
